[
  {
    "id": "1",
    "majorProject": true,
    "type": "frontend",
    "title": "Kasa",
    "pics": ["Kasa_landing_page.jpg","Kasa_about_page.jpg","Kasa_about_page_mobile.jpg","Kasa_error_page.jpg","Kasa_error_page_mobile.jpg","Kasa_landing_page_mobile.jpg","Kasa_rental_page.jpg","Kasa_rental_page_mobile.jpg"],
    "fr": {
      "shortDescription": "Frontend d’un site fictif de location d’hébergement",
      "another": "blabla"
    },
    "en": {
      "shortDescription": "Frontend of a fictitious accommodation rental site",
      "another": "blabla"
    },
    "stacks": [ "React", "React-router", "Sass" ]
  },
  {
    "id": "2",
    "majorProject": true,
    "type": "backend",
    "title": "Mon Vieux Grimoire",
    "pics": ["Mon_vieux_grimoire_Postman_routes.jpg","Mon_vieux_grimoire_Postman_run.jpg","Mon_vieux_grimoire_MongoDB.jpg","Mon_vieux_grimoire_MongoDB_2.jpg"],
    "fr": {
      "shortDescription": "Backend d’un site fictif de notation de livres",
      "another": "blabla"
    },
    "en": {
      "shortDescription": "Backend of a fictitious book rating site",
      "another": "blabla"
    },
    "stacks": [ "Node", "Express", "MongoDB" ]
  },
  {
    "id": "3",
    "majorProject": false,
    "type": "full",
    "title": "FD-bot",
    "pics": ["FD-bot_commands.jpg","FD-bot_hero.jpg","FD-bot_item.jpg","FD-bot_pet.jpg","FD-bot_talent.jpg"],
    "fr": {
      "shortDescription": "Bot pour Discord",
      "another": "blabla"
    },
    "en": {
      "shortDescription": "Discord bot",
      "another": "blabla"
    },
    "stacks": [ "Python", "Discord" ]
  }
]